ampel/_metapackage.py
ampel-0.8.3a2.dist-info/METADATA
ampel-0.8.3a2.dist-info/WHEEL
ampel-0.8.3a2.dist-info/LICENSE
ampel-0.8.3a2.dist-info/RECORD
