Metadata-Version: 2.1
Name: ampel
Version: 0.8.3a2
Summary: Asynchronous and Modular Platform with Execution Layers
Home-page: https://ampelproject.github.io
License: BSD-3-Clause
Author: Valery Brinnel
Maintainer: Jakob van Santen
Maintainer-email: jakob.van.santen@desy.de
Requires-Python: >=3.10,<3.12
Classifier: Development Status :: 4 - Beta
Classifier: Intended Audience :: Science/Research
Classifier: License :: OSI Approved :: BSD License
Classifier: Programming Language :: Python :: 3
Classifier: Programming Language :: Python :: 3.10
Classifier: Programming Language :: Python :: 3.11
Classifier: Topic :: Scientific/Engineering :: Information Analysis
Classifier: Typing :: Typed
Requires-Dist: ampel-core (>=0.8.3,<0.9.0)
Requires-Dist: ampel-ipython (==0.7)
Project-URL: Documentation, https://ampelproject.github.io
Project-URL: Repository, https://github.com/AmpelProject/Ampel-core
